{
  "main": {
    "id": "77a9a6b120b55038",
    "type": "split",
    "children": [
      {
        "id": "fd6e504be77fba7c",
        "type": "tabs",
        "children": [
          {
            "id": "ab05ed746f2a6e93",
            "type": "leaf",
            "state": {
              "type": "markdown",
              "state": {
                "file": "es/index.md",
                "mode": "source",
                "source": false
              },
              "icon": "lucide-file",
              "title": "index"
            }
          }
        ]
      }
    ],
    "direction": "vertical"
  },
  "left": {
    "id": "288910d98b90029d",
    "type": "split",
    "children": [
      {
        "id": "ef3f33171ab6935f",
        "type": "tabs",
        "children": [
          {
            "id": "6778317d1ece19c3",
            "type": "leaf",
            "state": {
              "type": "file-explorer",
              "state": {
                "sortOrder": "alphabetical",
                "autoReveal": false
              },
              "icon": "lucide-folder-closed",
              "title": "Files"
            }
          },
          {
            "id": "470871710e4f1762",
            "type": "leaf",
            "state": {
              "type": "search",
              "state": {
                "query": "",
                "matchingCase": false,
                "explainSearch": false,
                "collapseAll": false,
                "extraContext": false,
                "sortOrder": "alphabetical"
              },
              "icon": "lucide-search",
              "title": "Search"
            }
          },
          {
            "id": "7d9c235d5d55f148",
            "type": "leaf",
            "state": {
              "type": "bookmarks",
              "state": {},
              "icon": "lucide-bookmark",
              "title": "Bookmarks"
            }
          }
        ]
      }
    ],
    "direction": "horizontal",
    "width": 300
  },
  "right": {
    "id": "916a8c5d4da4a7e1",
    "type": "split",
    "children": [
      {
        "id": "033a9a9ca798d68f",
        "type": "tabs",
        "children": [
          {
            "id": "735c33b0622ee332",
            "type": "leaf",
            "state": {
              "type": "backlink",
              "state": {
                "file": "es/index.md",
                "collapseAll": false,
                "extraContext": false,
                "sortOrder": "alphabetical",
                "showSearch": false,
                "searchQuery": "",
                "backlinkCollapsed": false,
                "unlinkedCollapsed": true
              },
              "icon": "links-coming-in",
              "title": "Backlinks for index"
            }
          },
          {
            "id": "e3d50a37d93e9757",
            "type": "leaf",
            "state": {
              "type": "outgoing-link",
              "state": {
                "file": "es/index.md",
                "linksCollapsed": false,
                "unlinkedCollapsed": true
              },
              "icon": "links-going-out",
              "title": "Outgoing links from index"
            }
          },
          {
            "id": "ac128cd81dd002a2",
            "type": "leaf",
            "state": {
              "type": "tag",
              "state": {
                "sortOrder": "frequency",
                "useHierarchy": true,
                "showSearch": false,
                "searchQuery": ""
              },
              "icon": "lucide-tags",
              "title": "Tags"
            }
          },
          {
            "id": "861b7eb14b11784d",
            "type": "leaf",
            "state": {
              "type": "all-properties",
              "state": {
                "sortOrder": "frequency",
                "showSearch": false,
                "searchQuery": ""
              },
              "icon": "lucide-archive",
              "title": "All properties"
            }
          },
          {
            "id": "dc2325e06054dab6",
            "type": "leaf",
            "state": {
              "type": "outline",
              "state": {
                "file": "es/index.md",
                "followCursor": false,
                "showSearch": false,
                "searchQuery": ""
              },
              "icon": "lucide-list",
              "title": "Outline of index"
            }
          }
        ]
      }
    ],
    "direction": "horizontal",
    "width": 300,
    "collapsed": true
  },
  "left-ribbon": {
    "hiddenItems": {
      "switcher:Open quick switcher": false,
      "graph:Open graph view": false,
      "canvas:Create new canvas": false,
      "daily-notes:Open today's daily note": false,
      "templates:Insert template": false,
      "command-palette:Open command palette": false,
      "bases:Create new base": false
    }
  },
  "active": "6778317d1ece19c3",
  "lastOpenFiles": [
    "es"
  ]
}